intentlang/__init__.py
intentlang/engines/__init__.py
intentlang/engines/llm_engine.py
intentlang/executor.py
intentlang/handlers/__init__.py
intentlang/handlers/store.py
intentlang/intent.py
intentlang/magic.py
intentlang/models.py
intentlang/prompts/feedback.xml
intentlang/prompts/intent.xml
intentlang/prompts/llm_instruction.md
intentlang/prompts/runtime_context.xml
intentlang/runtime.py
intentlang/tools/__init__.py
intentlang/tools/reason.py
intentlang/utils.py
intentlang-0.2.7.dist-info/WHEEL
intentlang-0.2.7.dist-info/entry_points.txt
intentlang-0.2.7.dist-info/METADATA
intentlang-0.2.7.dist-info/RECORD
