Metadata-Version: 2.3
Name: intentlang
Version: 0.2.7
Summary: https://github.com/l3yx/intentlang
Author: leixiao
Author-email: leixiao <1729888211@qq.com>
Requires-Dist: jinja2>=3.1.6
Requires-Dist: openai>=2.14.0
Requires-Dist: pydantic>=2.12.5
Requires-Dist: python-dotenv>=1.0.0
Requires-Python: >=3.10
